helloworld.py
helloworldbygov.py
helloworldbygov-0.0.1.dist-info/LICENSE
helloworldbygov-0.0.1.dist-info/METADATA
helloworldbygov-0.0.1.dist-info/WHEEL
helloworldbygov-0.0.1.dist-info/top_level.txt
helloworldbygov-0.0.1.dist-info/RECORD
