Metadata-Version: 2.1
Name: helloworldbygov
Version: 0.0.1
Summary: Say hello!
Home-page: https://github.com/governorbaloyi/helloworld
Author: Governor Baloyi
Author-email: governor.baloyi@gmail.com
License: UNKNOWN
Platform: UNKNOWN
Classifier: Programming Language :: Python :: 3
Classifier: Programming Language :: Python :: 3.6
Classifier: Programming Language :: Python :: 3.7
Classifier: License :: OSI Approved :: GNU General Public License v2 or later (GPLv2+)
Classifier: Operating System :: OS Independent
Provides-Extra: dev
Requires-Dist: pytest (>=3.7) ; extra == 'dev'
Requires-Dist: twine ; extra == 'dev'
